[
    {
        "id": "specialist_23630821156",
        "title": "Blusa de frio feminina estilo blogueirinha moda 2023",
        "price": 69.9,
        "old_price": 87.375,
        "discount": 25,
        "image": "https://cf.shopee.com.br/file/br-11134207-81z1k-mi7ily9m49oi91",
        "link": "https://s.shopee.com.br/4LFR7y6wqB?utm_source=an_18318830863",
        "store": "Shopee",
        "category": "Premium"
    },
    {
        "id": "specialist_20168639262",
        "title": "casaco bleizer feminino LONGO máx p m g gg sobretudo",
        "price": 27.9,
        "old_price": 34.875,
        "discount": 25,
        "image": "https://cf.shopee.com.br/file/br-11134207-7qukw-liaxrkjtx4xh5d",
        "link": "https://s.shopee.com.br/BPsAR6JM9?utm_source=an_18318830863",
        "store": "Shopee",
        "category": "Premium"
    },
    {
        "id": "specialist_17592293309",
        "title": "KIT 3 ou 1 Unidade Cropped Feminino Canelado Golinha Básica Moda Verão Diversas Cores Carnaval Praia",
        "price": 26.99,
        "old_price": 33.7375,
        "discount": 25,
        "image": "https://cf.shopee.com.br/file/br-11134207-81z1k-mg4i535g38xw8b",
        "link": "https://s.shopee.com.br/4Aw0vmr5F3?utm_source=an_18318830863",
        "store": "Shopee",
        "category": "Premium"
    },
    {
        "id": "specialist_52707355082",
        "title": "Vestido longo casual básico feminino ribana manga canelada muscle fashion gringa preto marrom",
        "price": 39.99,
        "old_price": 49.987500000000004,
        "discount": 25,
        "image": "https://cf.shopee.com.br/file/br-11134207-820lf-mnd8dwqp0jk180",
        "link": "https://s.shopee.com.br/6VJvhK1K6w?utm_source=an_18318830863",
        "store": "Shopee",
        "category": "Premium"
    },
    {
        "id": "specialist_27568724319",
        "title": "Conjuntos de manga longa em torno do pescoço impresso moletom e leggings",
        "price": 98.33,
        "old_price": 122.9125,
        "discount": 25,
        "image": "https://cf.shopee.com.br/file/sg-11134201-8261c-mjr90j7wr0na4a",
        "link": "https://s.shopee.com.br/40cajM8DW5?utm_source=an_18318830863",
        "store": "Shopee",
        "category": "Premium"
    },
    {
        "id": "specialist_21798141466",
        "title": "Bady Doll Pijama Personagens Estampado Suede Com Detalhe de Renda Roupa de Dormir Top Doll",
        "price": 19.9,
        "old_price": 24.875,
        "discount": 25,
        "image": "https://cf.shopee.com.br/file/sg-11134201-7rd4q-m7vjiwral0fsaa",
        "link": "https://s.shopee.com.br/3fzkKrszGA?utm_source=an_18318830863",
        "store": "Shopee",
        "category": "Premium"
    },
    {
        "id": "specialist_22293929581",
        "title": "Body Regata Feminino Bory com Bojo Tecido Ribana Prime CONFORTAVEL",
        "price": 27.29,
        "old_price": 34.1125,
        "discount": 25,
        "image": "https://cf.shopee.com.br/file/br-11134207-820mh-mo9r4b0rbq4m45",
        "link": "https://s.shopee.com.br/8V505kaaRX?utm_source=an_18318830863",
        "store": "Shopee",
        "category": "Premium"
    },
    {
        "id": "specialist_58201848804",
        "title": "Conjunto Social TOMARA QUE CAIA CALÇA PANTALONA Alfaiataria Feminino",
        "price": 84.99,
        "old_price": 106.2375,
        "discount": 25,
        "image": "https://cf.shopee.com.br/file/br-11134207-81zui-ml1ke3fan2tdf7",
        "link": "https://s.shopee.com.br/5VROWJO3cl?utm_source=an_18318830863",
        "store": "Shopee",
        "category": "Premium"
    },
    {
        "id": "specialist_18899841725",
        "title": "Conjunto Feminino Casual Blusa e Saia Inverno Modelador Canelado Gola Alta Elegante Aconchegante",
        "price": 139.9,
        "old_price": 174.875,
        "discount": 25,
        "image": "https://cf.shopee.com.br/file/br-11134207-81z1k-mggx7t1yohdxfb",
        "link": "https://s.shopee.com.br/4fsHWa5gAH?utm_source=an_18318830863",
        "store": "Shopee",
        "category": "Premium"
    },
    {
        "id": "specialist_22694184762",
        "title": "Conjunto Feminino Uma Alça Social Duna Elegante Blusa Nula Manga e Calça Pantalona Alfaiataria Mula Manca Moda Promoção",
        "price": 59.9,
        "old_price": 74.875,
        "discount": 25,
        "image": "https://cf.shopee.com.br/file/br-11134207-81ztc-mj3ehjyk8qgx01",
        "link": "https://s.shopee.com.br/60Nf79k6Vo?utm_source=an_18318830863",
        "store": "Shopee",
        "category": "Premium"
    },
    {
        "id": "specialist_22397359976",
        "title": "Par Meia Média Compressão Varizes Pernas Cansadas Inchaço Dores 3/4 Zíper 20-30 Mmhg Compressão Unissex",
        "price": 16.9,
        "old_price": 21.125,
        "discount": 25,
        "image": "https://cf.shopee.com.br/file/br-11134207-7r98o-m8lzhvsnohyp38",
        "link": "https://s.shopee.com.br/7ppJIbFAsz?utm_source=an_18318830863",
        "store": "Shopee",
        "category": "Premium"
    },
    {
        "id": "specialist_15947138937",
        "title": "Conjuntos Feminino com Capuz  Inverno Agasalho Moda Blogueira Look para o frio",
        "price": 70.99,
        "old_price": 88.7375,
        "discount": 25,
        "image": "https://cf.shopee.com.br/file/br-11134207-820lo-mnoiew1bmewxcb",
        "link": "https://s.shopee.com.br/20rWLnzKdQ?utm_source=an_18318830863",
        "store": "Shopee",
        "category": "Premium"
    },
    {
        "id": "specialist_22199344913",
        "title": "Conjunto feminino shorts e blusinha moda verão básico",
        "price": 39.0,
        "old_price": 48.75,
        "discount": 25,
        "image": "https://cf.shopee.com.br/file/br-11134207-81z1k-mggx7t1yohdxfb",
        "link": "https://s.shopee.com.br/4fsHWhpBEC?utm_source=an_18318830863",
        "store": "Shopee",
        "category": "Premium"
    },
    {
        "id": "specialist_57456291160",
        "title": "Regata Feminina Brasil Copa Canelada Bandeira Camiseta Blusinha Torcida Verão Mulher Br Básica Algodão Moda Blogueira",
        "price": 35.99,
        "old_price": 44.987500000000004,
        "discount": 25,
        "image": "https://cf.shopee.com.br/file/br-11134207-81ztc-mjpmqhbosj5t6b",
        "link": "https://s.shopee.com.br/7ppJIWd7n5?utm_source=an_18318830863",
        "store": "Shopee",
        "category": "Premium"
    },
    {
        "id": "specialist_23494047705",
        "title": "Meia de Compressão Varizes Pernas Cansadas Inchaço Dores 3/4 Zíper Compressão Unissex",
        "price": 27.99,
        "old_price": 34.9875,
        "discount": 25,
        "image": "https://cf.shopee.com.br/file/sg-11134201-82614-mka9kmf7kiyud6",
        "link": "https://s.shopee.com.br/3LMtw8Akqq?utm_source=an_18318830863",
        "store": "Shopee",
        "category": "Premium"
    },
    {
        "id": "specialist_23094417104",
        "title": "Macacão Fitness Academia Poliamida Feminino Zero Transparencia 2",
        "price": 99.0,
        "old_price": 123.75,
        "discount": 25,
        "image": "https://cf.shopee.com.br/file/br-11134207-820m2-mmt3hs82gc8w03",
        "link": "https://s.shopee.com.br/2g7D8HFutN?utm_source=an_18318830863",
        "store": "Shopee",
        "category": "Premium"
    },
    {
        "id": "specialist_23898670446",
        "title": "KIT 3 Blusas Feminina Manga Longa Cacharrel Confortável Básico Gola Alta",
        "price": 58.81,
        "old_price": 73.5125,
        "discount": 25,
        "image": "https://cf.shopee.com.br/file/br-11134207-81z1k-mgr8dm2k0qv83e",
        "link": "https://s.shopee.com.br/7fVt6Ddl8z?utm_source=an_18318830863",
        "store": "Shopee",
        "category": "Premium"
    },
    {
        "id": "specialist_53606178917",
        "title": "Blusa T-Shirt Camiseta Brasil Feminina Manga Curta Copa Do Mundo Moda Verão",
        "price": 29.9,
        "old_price": 37.375,
        "discount": 25,
        "image": "https://cf.shopee.com.br/file/br-11134207-81ztd-mkzpuuhzqbk021",
        "link": "https://s.shopee.com.br/AUq4TQSyNr?utm_source=an_18318830863",
        "store": "Shopee",
        "category": "Premium"
    },
    {
        "id": "specialist_23794626758",
        "title": "Vestido Longo Evangélico Feminino Comportado para Igreja Dia a Dia Passeio Elegante",
        "price": 68.99,
        "old_price": 86.2375,
        "discount": 25,
        "image": "https://cf.shopee.com.br/file/br-11134207-81z1k-mgfu3v2f9af83f",
        "link": "https://s.shopee.com.br/1qY69UzxyN?utm_source=an_18318830863",
        "store": "Shopee",
        "category": "Premium"
    },
    {
        "id": "specialist_23491605753",
        "title": "Calça Skinny Com Cinto Malha Crepe Cintura Alta do P ao G3",
        "price": 35.06,
        "old_price": 43.825,
        "discount": 25,
        "image": "https://cf.shopee.com.br/file/br-11134207-7r98o-loefhxkk0gixf6",
        "link": "https://s.shopee.com.br/7AZcVNHiDs?utm_source=an_18318830863",
        "store": "Shopee",
        "category": "Premium"
    },
    {
        "id": "specialist_21399703181",
        "title": "calça pantalona social com pasante tecido sensorial",
        "price": 69.0,
        "old_price": 86.25,
        "discount": 25,
        "image": "https://cf.shopee.com.br/file/br-11134207-7r98o-mabzsggfabau8a",
        "link": "https://s.shopee.com.br/2LUMkPy3xW?utm_source=an_18318830863",
        "store": "Shopee",
        "category": "Premium"
    },
    {
        "id": "specialist_27337964832",
        "title": "Macacão Feminino Longo Alfaiataria Pantalona Premium Social Alça Fina com Bojo Sem Cinto Verão Moda Mulher Verão",
        "price": 59.89,
        "old_price": 74.8625,
        "discount": 25,
        "image": "https://cf.shopee.com.br/file/br-11134207-820lb-mmuw7niafgn44b",
        "link": "https://s.shopee.com.br/4Aw0v2ACpn?utm_source=an_18318830863",
        "store": "Shopee",
        "category": "Premium"
    },
    {
        "id": "specialist_15569121811",
        "title": "Blazer Feminino Casaquinho Maxi Longo Sobretudo Alfaiataria Social Blazer Com Botão",
        "price": 47.15,
        "old_price": 58.9375,
        "discount": 25,
        "image": "https://cf.shopee.com.br/file/br-11134207-7r98o-lwrhhtlzssc696",
        "link": "https://s.shopee.com.br/LjIMcMAx1?utm_source=an_18318830863",
        "store": "Shopee",
        "category": "Premium"
    },
    {
        "id": "specialist_20018437267",
        "title": "Conjunto Kimono Top Short Kimono Casual Elegante",
        "price": 53.63,
        "old_price": 67.03750000000001,
        "discount": 25,
        "image": "https://cf.shopee.com.br/file/br-11134207-81ztk-mkmg29o7jwu847",
        "link": "https://s.shopee.com.br/60Nf720bRd?utm_source=an_18318830863",
        "store": "Shopee",
        "category": "Premium"
    }
]