[
    {
        "id": "specialist_https://cf.shopee.com.br/file/br-11134207-7r98o-m04w44j9dynx36",
        "title": "Kit -Ninho Redutor de Berço + Capa de Bebê Conforto, Capota, Protetores de Cinto e Redutor Anatômico",
        "price": 152.91,
        "old_price": 191.1375,
        "discount": 25,
        "image": "https://cf.shopee.com.br/file/br-11134207-7r98o-locwu3cj0zopfd",
        "link": "https://shope.ee/an_redir?origin_link=https%3A%2F%2Fshopee.com.br%2Fproduct%2F1265595869%2F18199415609",
        "store": "Shopee",
        "category": "Premium"
    },
    {
        "id": "specialist_https://cf.shopee.com.br/file/br-11134207-820m5-mo9amrw7i5mp9b",
        "title": "Kit 6 Meias Soquete Algodão Unissex Conforto para o Dia a Dia, trabalho e academia",
        "price": 49.45,
        "old_price": 61.8125,
        "discount": 25,
        "image": "https://cf.shopee.com.br/file/br-11134207-81zu3-mklawf0bxxq935",
        "link": "https://shope.ee/an_redir?origin_link=https%3A%2F%2Fshopee.com.br%2Fproduct%2F1409242839%2F46910570541",
        "store": "Shopee",
        "category": "Premium"
    },
    {
        "id": "specialist_https://cf.shopee.com.br/file/sg-11134201-7rdws-ly5siztzf2ncef",
        "title": "Notebook Teclado Universal Film/Laptop Silicone À Prova De Poeira Película Protetora/D'água Claro",
        "price": 12.9,
        "old_price": 16.125,
        "discount": 25,
        "image": "https://cf.shopee.com.br/file/br-11134207-7r98o-lris8kb9e52z88",
        "link": "https://shope.ee/an_redir?origin_link=https%3A%2F%2Fshopee.com.br%2Fproduct%2F1279179278%2F23793173278",
        "store": "Shopee",
        "category": "Premium"
    },
    {
        "id": "specialist_https://cf.shopee.com.br/file/br-11134207-820lp-mo02c567da8227",
        "title": "Kit de Cintos Femininos Fivela Argola Tripla Dourada 3cm Blogueira Tendência Luxo - Cinto Feminino Para Calça Jeans",
        "price": 26.99,
        "old_price": 33.7375,
        "discount": 25,
        "image": "https://cf.shopee.com.br/file/br-11134207-7r98o-m9eqey30hipu96",
        "link": "https://shope.ee/an_redir?origin_link=https%3A%2F%2Fshopee.com.br%2Fproduct%2F973176089%2F45306148850",
        "store": "Shopee",
        "category": "Premium"
    },
    {
        "id": "specialist_https://cf.shopee.com.br/file/cn-11134207-7ras8-m16nllur8s4j1b",
        "title": "Camisa NewJeans Never Die ADORE",
        "price": 45.84,
        "old_price": 57.300000000000004,
        "discount": 25,
        "image": "https://cf.shopee.com.br/file/cn-11134207-7ras8-m16nllur8s4j1b",
        "link": "https://shope.ee/an_redir?origin_link=https%3A%2F%2Fshopee.com.br%2Fproduct%2F969555374%2F29113668399",
        "store": "Shopee",
        "category": "Premium"
    },
    {
        "id": "specialist_https://cf.shopee.com.br/file/br-11134207-7r98o-ma8sibxiy8qeec",
        "title": "Conjunto Melanie  Com Fenda lateral Super Confortável Forrado",
        "price": 25.99,
        "old_price": 32.4875,
        "discount": 25,
        "image": "https://cf.shopee.com.br/file/br-11134207-7r98o-ma8sibxiy8qeec",
        "link": "https://shope.ee/an_redir?origin_link=https%3A%2F%2Fshopee.com.br%2Fproduct%2F536525674%2F22593250754",
        "store": "Shopee",
        "category": "Premium"
    },
    {
        "id": "specialist_https://cf.shopee.com.br/file/sg-11134201-8260l-mkc9x6kqmrr455",
        "title": "Camiseta Baby Look Feminina Personal Fitness Academia Instrutor Professor Profissional Camisa Casual Treino",
        "price": 20.0,
        "old_price": 25.0,
        "discount": 25,
        "image": "https://cf.shopee.com.br/file/br-11134207-81z1k-mi3guvfpr18h49",
        "link": "https://shope.ee/an_redir?origin_link=https%3A%2F%2Fshopee.com.br%2Fproduct%2F1614162396%2F58254692713",
        "store": "Shopee",
        "category": "Premium"
    },
    {
        "id": "specialist_https://cf.shopee.com.br/file/cn-11134207-7r98o-ln43a8i4mfa139",
        "title": "Bonito Retro Denim Estilo Adesivos Manual Foto Diário Caderno Scrapbook Papelaria DIY Adesivos Decorativo",
        "price": 2.99,
        "old_price": 3.7375000000000003,
        "discount": 25,
        "image": "https://cf.shopee.com.br/file/cn-11134207-7r98o-ln43a8i4mfa139",
        "link": "https://shope.ee/an_redir?origin_link=https%3A%2F%2Fshopee.com.br%2Fproduct%2F1060420899%2F15399682248",
        "store": "Shopee",
        "category": "Premium"
    },
    {
        "id": "specialist_https://cf.shopee.com.br/file/br-11134207-7r98o-mba6zzbhk5n3b5",
        "title": "Moletom Devil May Cry Dante Caçador de Demônios Anime | Algodão Flanelado| Blusa de Frio Unissex",
        "price": 79.9,
        "old_price": 99.875,
        "discount": 25,
        "image": "https://cf.shopee.com.br/file/sg-11134201-824j2-mpid4j79dkw2c2",
        "link": "https://shope.ee/an_redir?origin_link=https%3A%2F%2Fshopee.com.br%2Fproduct%2F1430928433%2F22894167331",
        "store": "Shopee",
        "category": "Premium"
    },
    {
        "id": "specialist_https://cf.shopee.com.br/file/br-11134207-7r98o-m5j0kpmc5dbm71",
        "title": "CARNAVAL short saia ( vem com shorts )feminina com strass (903)",
        "price": 79.99,
        "old_price": 99.9875,
        "discount": 25,
        "image": "https://cf.shopee.com.br/file/br-11134207-7r98o-m5j0kpmc5dbm71",
        "link": "https://shope.ee/an_redir?origin_link=https%3A%2F%2Fshopee.com.br%2Fproduct%2F429861881%2F22593670149",
        "store": "Shopee",
        "category": "Premium"
    },
    {
        "id": "specialist_https://cf.shopee.com.br/file/br-11134207-7r98o-masfsjshcxovd1",
        "title": "TB Moda Conjunto Pulseira Anel Brincos de Metal Exagerada em Ouro com Design de Gota Água Acessório",
        "price": 9.94,
        "old_price": 12.424999999999999,
        "discount": 25,
        "image": "https://cf.shopee.com.br/file/sg-11134201-8259w-mg13deybfp5b27",
        "link": "https://shope.ee/an_redir?origin_link=https%3A%2F%2Fshopee.com.br%2Fproduct%2F1542122883%2F18898214685",
        "store": "Shopee",
        "category": "Premium"
    },
    {
        "id": "specialist_https://cf.shopee.com.br/file/sg-11134201-81zwr-mmq3tb4nxreqe4",
        "title": "OLEO LABIAL HIDRATANTE JELLY BERRY POP RUBY KISSES COM TEXTURA LEVE",
        "price": 19.9,
        "old_price": 24.875,
        "discount": 25,
        "image": "https://cf.shopee.com.br/file/sg-11134201-81zw4-mmkl4c4bt7uq3b",
        "link": "https://shope.ee/an_redir?origin_link=https%3A%2F%2Fshopee.com.br%2Fproduct%2F1432989474%2F58208276481",
        "store": "Shopee",
        "category": "Premium"
    },
    {
        "id": "specialist_https://cf.shopee.com.br/file/br-11134207-7r98o-mad46rt1yljj16",
        "title": "Cauter Gloss Espelhamento e Blindagem Cuticular 500ml Borabella",
        "price": 66.9,
        "old_price": 83.625,
        "discount": 25,
        "image": "https://cf.shopee.com.br/file/br-11134207-7r98o-lxcjo8fd6nr30f",
        "link": "https://shope.ee/an_redir?origin_link=https%3A%2F%2Fshopee.com.br%2Fproduct%2F563703728%2F21298579036",
        "store": "Shopee",
        "category": "Premium"
    },
    {
        "id": "specialist_https://cf.shopee.com.br/file/sg-11134201-8262r-mlqtevsdsq2q82",
        "title": "Kit Apse 3 itens Shampoo, Condicionador e Ativador Modelador Creme de Pentear CACHOS - Apice",
        "price": 109.8,
        "old_price": 137.25,
        "discount": 25,
        "image": "https://cf.shopee.com.br/file/sg-11134201-8262r-mlqtevsdsq2q82",
        "link": "https://shope.ee/an_redir?origin_link=https%3A%2F%2Fshopee.com.br%2Fproduct%2F1413292509%2F22698137720",
        "store": "Shopee",
        "category": "Premium"
    },
    {
        "id": "specialist_https://cf.shopee.com.br/file/br-11134207-820me-mmp1df1kkirk89",
        "title": "Pijama Infantil Manga longa Menino Tamanho 2 a 10  Anos Malha 100% Algodão",
        "price": 35.99,
        "old_price": 44.987500000000004,
        "discount": 25,
        "image": "https://cf.shopee.com.br/file/br-11134207-820m1-mog3bmpu8fswb0",
        "link": "https://shope.ee/an_redir?origin_link=https%3A%2F%2Fshopee.com.br%2Fproduct%2F391306526%2F18499698279",
        "store": "Shopee",
        "category": "Premium"
    },
    {
        "id": "specialist_https://cf.shopee.com.br/file/br-11134207-7r98o-mbnvu7c1xe8pd4",
        "title": "Calça Feminina Boca de Sino Flare Jackard com Bolso na Frente",
        "price": 69.6,
        "old_price": 87.0,
        "discount": 25,
        "image": "https://cf.shopee.com.br/file/br-11134207-820l6-mnhqzwz52dxdc4",
        "link": "https://shope.ee/an_redir?origin_link=https%3A%2F%2Fshopee.com.br%2Fproduct%2F446507650%2F22498689800",
        "store": "Shopee",
        "category": "Premium"
    },
    {
        "id": "specialist_https://cf.shopee.com.br/file/br-11134207-820lc-moh89h4m0feu6c",
        "title": "Kit Tênis Calce Facil Esportivo Academia + Fone + Relógio",
        "price": 64.9,
        "old_price": 81.125,
        "discount": 25,
        "image": "https://cf.shopee.com.br/file/br-11134207-7r98o-m0974iv89ug973",
        "link": "https://shope.ee/an_redir?origin_link=https%3A%2F%2Fshopee.com.br%2Fproduct%2F1607315105%2F58261061473",
        "store": "Shopee",
        "category": "Premium"
    },
    {
        "id": "specialist_https://cf.shopee.com.br/file/br-11134207-820mh-mnyzaxh6hypwe6",
        "title": "Camisola sem Bojo Feminina Renda Lingerie Pijama Noite Soltinha Moda Adulta Confortavel",
        "price": 16.98,
        "old_price": 21.225,
        "discount": 25,
        "image": "https://cf.shopee.com.br/file/br-11134207-7r98o-m79hb0f8rkuid2",
        "link": "https://shope.ee/an_redir?origin_link=https%3A%2F%2Fshopee.com.br%2Fproduct%2F1165664743%2F22698868483",
        "store": "Shopee",
        "category": "Premium"
    },
    {
        "id": "specialist_https://cf.shopee.com.br/file/sg-11134201-7raup-mb6h5xq9u2k672",
        "title": "6 Unidades/Conjunto  Kit De Disco De Polimento De Resina Composta",
        "price": 52.24,
        "old_price": 65.3,
        "discount": 25,
        "image": "https://cf.shopee.com.br/file/sg-11134201-7rdvp-mcvuwyc3r67w83",
        "link": "https://shope.ee/an_redir?origin_link=https%3A%2F%2Fshopee.com.br%2Fproduct%2F443280943%2F42455164464",
        "store": "Shopee",
        "category": "Premium"
    },
    {
        "id": "specialist_https://cf.shopee.com.br/file/sg-11134201-824g2-mfoic598uqz14b",
        "title": "24/36/48/60/80 peças Caneta Marcadora De Ponta Dupla Conjunto De Canetas De Aquarela Especial-",
        "price": 19.98,
        "old_price": 24.975,
        "discount": 25,
        "image": "https://cf.shopee.com.br/file/br-11134207-81z1k-meqhvgv5lfr633",
        "link": "https://shope.ee/an_redir?origin_link=https%3A%2F%2Fshopee.com.br%2Fproduct%2F1649593273%2F22894520104",
        "store": "Shopee",
        "category": "Premium"
    },
    {
        "id": "specialist_https://cf.shopee.com.br/file/sg-11134201-7rdxe-mcjjdim2ip4jf3",
        "title": "Kit Sortido 3 Camisetas Infantil Feminino Avulso",
        "price": 49.9,
        "old_price": 62.375,
        "discount": 25,
        "image": "https://cf.shopee.com.br/file/br-11134207-7r98o-mava8s15dbwvf0",
        "link": "https://shope.ee/an_redir?origin_link=https%3A%2F%2Fshopee.com.br%2Fproduct%2F717393801%2F41309745422",
        "store": "Shopee",
        "category": "Premium"
    },
    {
        "id": "specialist_https://cf.shopee.com.br/file/sg-11134201-7rd6y-m7igjsk9xrsf40",
        "title": "Saia De Courino Feminino Gode Longa Cintura Alta 333",
        "price": 89.99,
        "old_price": 112.4875,
        "discount": 25,
        "image": "https://cf.shopee.com.br/file/sg-11134201-7rd6y-m7igjsk9xrsf40",
        "link": "https://shope.ee/an_redir?origin_link=https%3A%2F%2Fshopee.com.br%2Fproduct%2F1310072055%2F23898323645",
        "store": "Shopee",
        "category": "Premium"
    },
    {
        "id": "specialist_https://cf.shopee.com.br/file/sg-11134201-7rfgi-m3llv0vdv9999f",
        "title": "Moda Gola Falsa Branco Preto Blusa Camisola Destacável Camisa Feminina Algodão Lapela Topo Acessórios De Roupas Feminina",
        "price": 19.04,
        "old_price": 23.799999999999997,
        "discount": 25,
        "image": "https://cf.shopee.com.br/file/sg-11134201-824ga-mpmu416sye4r72",
        "link": "https://shope.ee/an_redir?origin_link=https%3A%2F%2Fshopee.com.br%2Fproduct%2F364518585%2F28070248661",
        "store": "Shopee",
        "category": "Premium"
    },
    {
        "id": "specialist_https://cf.shopee.com.br/file/br-11134207-820l5-mowovyniwfetb2",
        "title": "Camiseta tradicional camisa feminina100%algodão natureza brasilidades delicada brasil futebol",
        "price": 29.9,
        "old_price": 37.375,
        "discount": 25,
        "image": "https://cf.shopee.com.br/file/br-11134207-820mb-mosl4pffaepv7a",
        "link": "https://shope.ee/an_redir?origin_link=https%3A%2F%2Fshopee.com.br%2Fproduct%2F1697195803%2F58261708609",
        "store": "Shopee",
        "category": "Premium"
    }
]