[
    {
        "id": "sens_1777582908_308",
        "title": "Óleo de Massagem Coporal Red Apple Relaxante Hidratante Aromático Perfumado Provoke-me",
        "price": 71.9,
        "old_price": 97.07,
        "discount": 35,
        "store": "Shopee",
        "category": "Cosmética Sensorial",
        "image": "https://cf.shopee.com.br/file/br-11134207-81z1k-mf34tifhiqkm2a",
        "link": "https://s.shopee.com.br/2VoCcc40eZ?utm_source=an_18318830863",
        "tags": [
            "#elixir"
        ],
        "reason": "Titanium Choice: Bem-Estar Íntimo",
        "added_date": "2026-04-30",
        "quality_score": 127.59272592076569
    },
    {
        "id": "sens_1777582912_855",
        "title": "Banho Relaxante Hidratante | Banho e Pós-Banho | Aromaterapia | Vela de Massagem 100% Natural",
        "price": 35.9,
        "old_price": 48.47,
        "discount": 35,
        "store": "Shopee",
        "category": "Cosmética Sensorial",
        "image": "https://cf.shopee.com.br/file/br-11134207-7r98o-mb1s08evmk5rc0",
        "link": "https://s.shopee.com.br/6AhUzM7a3n?utm_source=an_18318830863",
        "tags": [
            "#zen"
        ],
        "reason": "Titanium Choice: Bem-Estar Íntimo",
        "added_date": "2026-04-30",
        "quality_score": 100.29677744719112
    },
    {
        "id": "sens_1777582895_217",
        "title": "Baby Doll Cetim Com Renda Luxo Para Dormir Babydoll",
        "price": 99.9,
        "old_price": 134.87,
        "discount": 35,
        "store": "Shopee",
        "category": "Moda & Luxo",
        "image": "https://cf.shopee.com.br/file/73fc330589eea4813349f22f79cf30da",
        "link": "https://s.shopee.com.br/qfydXIwGT?utm_source=an_18318830863",
        "tags": [
            "#sleepwear"
        ],
        "reason": "Titanium Choice: Bem-Estar Íntimo",
        "added_date": "2026-04-30",
        "quality_score": 127.22551442080633
    },
    {
        "id": "sens_1777582912_356",
        "title": "Vela de Massagem | Vela Hidratante | Vela Relaxante | Aromaterapia",
        "price": 19.0,
        "old_price": 25.65,
        "discount": 35,
        "store": "Shopee",
        "category": "Cosmética Sensorial",
        "image": "https://cf.shopee.com.br/file/br-11134207-7r98o-m8lzyouq21shd8",
        "link": "https://s.shopee.com.br/7fWIm71s1A?utm_source=an_18318830863",
        "tags": [
            "#zen"
        ],
        "reason": "Titanium Choice: Bem-Estar Íntimo",
        "added_date": "2026-04-30",
        "quality_score": 85.39885218802755
    },
    {
        "id": "sens_1777582899_707",
        "title": "Body De Renda Sensual Coleção Íntima de Luxo Espera Marido Sem Bojo Aberto Transparente Feminino Moda Íntima Luxo",
        "price": 18.99,
        "old_price": 25.64,
        "discount": 35,
        "store": "Shopee",
        "category": "Moda & Luxo",
        "image": "https://cf.shopee.com.br/file/br-11134207-81zte-mkv8bmpi6ebk18",
        "link": "https://s.shopee.com.br/9UxwxSzh7s?utm_source=an_18318830863",
        "tags": [
            "#fashion"
        ],
        "reason": "Titanium Choice: Bem-Estar Íntimo",
        "added_date": "2026-04-30",
        "quality_score": 88.29180847800326
    },
    {
        "id": "sens_1777582902_497",
        "title": "Robe,roupão em cetim LUXO ,noiva ,casamento,madrinha,camisola,hobby,pijama,seda,kimono,feminima",
        "price": 46.87,
        "old_price": 63.27,
        "discount": 35,
        "store": "Shopee",
        "category": "Moda & Luxo",
        "image": "https://cf.shopee.com.br/file/br-11134207-7r98o-lq95ms23uc6fb4",
        "link": "https://s.shopee.com.br/2g7coucMEy?utm_source=an_18318830863",
        "tags": [
            "#boutique"
        ],
        "reason": "Titanium Choice: Bem-Estar Íntimo",
        "added_date": "2026-04-30",
        "quality_score": 100.40254480495892
    },
    {
        "id": "sens_1777582915_207",
        "title": "Cuide-se Bem Cereja Livre (o Boticário): Spray Íntimo, Loção Hidratante, Lenço Umedecido, Body Splash, Creme Virilha e +",
        "price": 62.9,
        "old_price": 84.92,
        "discount": 35,
        "store": "Shopee",
        "category": "Cosmética Sensorial",
        "image": "https://cf.shopee.com.br/file/br-11134207-7r98o-lxime747qut2da",
        "link": "https://s.shopee.com.br/9KeWlB8iz4?utm_source=an_18318830863",
        "tags": [
            "#care"
        ],
        "reason": "Titanium Choice: Bem-Estar Íntimo",
        "added_date": "2026-04-30",
        "quality_score": 116.51290778584229
    },
    {
        "id": "sens_1777582912_204",
        "title": "Vela Aromática & Massagem Ritos Lemongrass 160 G",
        "price": 125.9,
        "old_price": 169.97,
        "discount": 35,
        "store": "Shopee",
        "category": "Cosmética Sensorial",
        "image": "https://cf.shopee.com.br/file/br-11134207-7r98o-lo1bmbvcspexda",
        "link": "https://s.shopee.com.br/5flEOR9U4i?utm_source=an_18318830863",
        "tags": [
            "#zen"
        ],
        "reason": "Titanium Choice: Bem-Estar Íntimo",
        "added_date": "2026-04-30",
        "quality_score": 161.34223550204572
    },
    {
        "id": "sens_1777582902_287",
        "title": "3 Robe luxo noiva/debutante ,roupão  cetim LUXO ,noiva ,casamento,madrinha,camisola,hobby,pijama,seda,kimono",
        "price": 108.64,
        "old_price": 146.66,
        "discount": 35,
        "store": "Shopee",
        "category": "Moda & Luxo",
        "image": "https://cf.shopee.com.br/file/br-11134207-7r98o-m1o7q4ewo4co80",
        "link": "https://s.shopee.com.br/3VgjoRZBYD?utm_source=an_18318830863",
        "tags": [
            "#boutique"
        ],
        "reason": "Titanium Choice: Bem-Estar Íntimo",
        "added_date": "2026-04-30",
        "quality_score": 160.40131364364203
    },
    {
        "id": "sens_1777582902_788",
        "title": "10 Robe,roupão em cetim LUXO ,noiva ,casamento,madrinha,camisola,hobby,pijama,seda,kimono",
        "price": 384.99,
        "old_price": 519.74,
        "discount": 35,
        "store": "Shopee",
        "category": "Moda & Luxo",
        "image": "https://cf.shopee.com.br/file/br-11134207-7r98o-ls9rm72dhq8dd3",
        "link": "https://s.shopee.com.br/30kTDWb5Z4?utm_source=an_18318830863",
        "tags": [
            "#boutique"
        ],
        "reason": "Titanium Choice: Bem-Estar Íntimo",
        "added_date": "2026-04-30",
        "quality_score": 330.67347847486053
    },
    {
        "id": "sens_1777582892_499",
        "title": "Calcinha Modeladora Cós Alto Suplex Compressão Fio Dental Luxo Feminina Preta Bege Renda",
        "price": 21.9,
        "old_price": 29.57,
        "discount": 35,
        "store": "Shopee",
        "category": "Moda & Luxo",
        "image": "https://cf.shopee.com.br/file/br-11134207-7r98o-m5mwy422qbhuef",
        "link": "https://s.shopee.com.br/AUqU9IPvBb?utm_source=an_18318830863",
        "tags": [
            "#lingerie"
        ],
        "reason": "Titanium Choice: Bem-Estar Íntimo",
        "added_date": "2026-04-30",
        "quality_score": 90.62567292064277
    },
    {
        "id": "sens_1777582915_916",
        "title": "Kit Cuide-se Bem Cereja de Fases ( Spray Íntimo 75 ML + Creme Corporal 200g + Óleo Térmico Corporal 110 ML) O Boticário",
        "price": 229.9,
        "old_price": 310.37,
        "discount": 35,
        "store": "Shopee",
        "category": "Cosmética Sensorial",
        "image": "https://cf.shopee.com.br/file/sg-11134201-8261i-ml511hlmae4h31",
        "link": "https://s.shopee.com.br/AUqU9K4HcL?utm_source=an_18318830863",
        "tags": [
            "#care"
        ],
        "reason": "Titanium Choice: Bem-Estar Íntimo",
        "added_date": "2026-04-30",
        "quality_score": 237.83132191855168
    },
    {
        "id": "sens_1777582899_648",
        "title": "Body Fetiche Erótico Feminino Renda Sensual Coleção Íntima de Luxo Aberta Noite Especial Espera Marido Luxo",
        "price": 18.99,
        "old_price": 25.64,
        "discount": 35,
        "store": "Shopee",
        "category": "Moda & Luxo",
        "image": "https://cf.shopee.com.br/file/br-11134207-81zth-mkv8ulxq0zyb41",
        "link": "https://s.shopee.com.br/9zuDYNxn6v?utm_source=an_18318830863",
        "tags": [
            "#fashion"
        ],
        "reason": "Titanium Choice: Bem-Estar Íntimo",
        "added_date": "2026-04-30",
        "quality_score": 76.52698155106054
    },
    {
        "id": "sens_1777582912_529",
        "title": "Vela para Massagem Terapêutica e Pindas Chinesas Aromoterapia",
        "price": 119.0,
        "old_price": 160.65,
        "discount": 35,
        "store": "Shopee",
        "category": "Cosmética Sensorial",
        "image": "https://cf.shopee.com.br/file/br-11134207-7r98o-m6e02s374u2v4e",
        "link": "https://s.shopee.com.br/5VRoC8A7Pj?utm_source=an_18318830863",
        "tags": [
            "#zen"
        ],
        "reason": "Titanium Choice: Bem-Estar Íntimo",
        "added_date": "2026-04-30",
        "quality_score": 158.28207014535943
    },
    {
        "id": "sens_1777582915_913",
        "title": "Spray Intimo INTIMAMENT SERUM HIDRATANTE REJUVENESCEDOR INTIMO FEMININO 60ML Menopausa",
        "price": 36.79,
        "old_price": 49.67,
        "discount": 35,
        "store": "Shopee",
        "category": "Cosmética Sensorial",
        "image": "https://cf.shopee.com.br/file/br-11134207-7r98o-mahmf5rifxfd6d",
        "link": "https://s.shopee.com.br/9fHN9n7SJ6?utm_source=an_18318830863",
        "tags": [
            "#care"
        ],
        "reason": "Titanium Choice: Bem-Estar Íntimo",
        "added_date": "2026-04-30",
        "quality_score": 101.62215824853041
    },
    {
        "id": "sens_1777582892_567",
        "title": "Camisola Sexy Preta Renda Luxo Curta Coleção Íntima de Luxo Transparente Sensual Luvas + Calcinha Fio Dental",
        "price": 103.7,
        "old_price": 140.0,
        "discount": 35,
        "store": "Shopee",
        "category": "Moda & Luxo",
        "image": "https://cf.shopee.com.br/file/br-11134201-7r98o-mdun35gqbquxa0",
        "link": "https://s.shopee.com.br/AADdkgRBrV?utm_source=an_18318830863",
        "tags": [
            "#lingerie"
        ],
        "reason": "Titanium Choice: Bem-Estar Íntimo",
        "added_date": "2026-04-30",
        "quality_score": 137.3481918550318
    },
    {
        "id": "sens_1777582915_753",
        "title": "Kit Cereja de Fases Completo Hidratante + Body Splash + Spray Íntimo + Sabonete Feminino Doce",
        "price": 200.0,
        "old_price": 270.0,
        "discount": 35,
        "store": "Shopee",
        "category": "Cosmética Sensorial",
        "image": "https://cf.shopee.com.br/file/br-11134207-820mh-mlff3zjstwxyfd",
        "link": "https://s.shopee.com.br/9zuDYP6BdG?utm_source=an_18318830863",
        "tags": [
            "#care"
        ],
        "reason": "Titanium Choice: Bem-Estar Íntimo",
        "added_date": "2026-04-30",
        "quality_score": 194.65676223522544
    },
    {
        "id": "sens_1777582899_481",
        "title": "Body Feminino Cavado Renda Sensual Decotado Regata Luxo",
        "price": 39.9,
        "old_price": 53.87,
        "discount": 35,
        "store": "Shopee",
        "category": "Moda & Luxo",
        "image": "https://cf.shopee.com.br/file/sg-11134201-7rd6p-lwnai3geftzu8a",
        "link": "https://s.shopee.com.br/8KlzZK48UZ?utm_source=an_18318830863",
        "tags": [
            "#fashion"
        ],
        "reason": "Titanium Choice: Bem-Estar Íntimo",
        "added_date": "2026-04-30",
        "quality_score": 106.12051709714046
    },
    {
        "id": "sens_1777582892_885",
        "title": "Camisola Curta Preta Renda Coleção Íntima de Luxo Transparente Bojo Vestido Calcinha Luxo Decote",
        "price": 102.7,
        "old_price": 138.65,
        "discount": 35,
        "store": "Shopee",
        "category": "Moda & Luxo",
        "image": "https://cf.shopee.com.br/file/br-11134201-7r98o-mdun291zwqt558",
        "link": "https://s.shopee.com.br/AKX3wzQYWY?utm_source=an_18318830863",
        "tags": [
            "#lingerie"
        ],
        "reason": "Titanium Choice: Bem-Estar Íntimo",
        "added_date": "2026-04-30",
        "quality_score": 142.5587783228171
    },
    {
        "id": "sens_1777582902_413",
        "title": "kit noiva/debutante,7 Robe BORDADO ,roupão em cetim LUXO ,noiva ,casamento,madrinha,camisola,hobby,pijama,seda,kimono",
        "price": 438.9,
        "old_price": 592.51,
        "discount": 35,
        "store": "Shopee",
        "category": "Moda & Luxo",
        "image": "https://cf.shopee.com.br/file/br-11134207-7r98o-lr7ef7fw4cgdc7",
        "link": "https://s.shopee.com.br/2qR31Dbiu1?utm_source=an_18318830863",
        "tags": [
            "#boutique"
        ],
        "reason": "Titanium Choice: Bem-Estar Íntimo",
        "added_date": "2026-04-30",
        "quality_score": 356.56609613352526
    },
    {
        "id": "sens_1777582912_546",
        "title": "Kit Básico Vela Aromática para Massagem",
        "price": 267.8,
        "old_price": 361.53,
        "discount": 35,
        "store": "Shopee",
        "category": "Cosmética Sensorial",
        "image": "https://cf.shopee.com.br/file/br-11134207-7r98o-maeeszqm8wwf73",
        "link": "https://s.shopee.com.br/60O4n38DOk?utm_source=an_18318830863",
        "tags": [
            "#zen"
        ],
        "reason": "Titanium Choice: Bem-Estar Íntimo",
        "added_date": "2026-04-30",
        "quality_score": 272.4728814533472
    },
    {
        "id": "sens_1777582915_683",
        "title": "Creme Hidratante Para Virilha /Spray íntimo Cuide-se Bem Cereja 🍒 Livre 100ml oboticario.",
        "price": 55.0,
        "old_price": 74.25,
        "discount": 35,
        "store": "Shopee",
        "category": "Cosmética Sensorial",
        "image": "https://cf.shopee.com.br/file/br-11134207-7qukw-lh6v681m3jw51d",
        "link": "https://s.shopee.com.br/AADdki5YIJ?utm_source=an_18318830863",
        "tags": [
            "#care"
        ],
        "reason": "Titanium Choice: Bem-Estar Íntimo",
        "added_date": "2026-04-30",
        "quality_score": 105.70055146922287
    },
    {
        "id": "sens_1777582902_579",
        "title": "kit 2 Robe,roupão em cetim LUXO 5.5 ,noiva ,casamento,madrinha,camisola,hobby,pijama,seda,kimono,feminino,roupa intima",
        "price": 76.24,
        "old_price": 102.92,
        "discount": 35,
        "store": "Shopee",
        "category": "Moda & Luxo",
        "image": "https://cf.shopee.com.br/file/br-11134207-7r98o-lph16ntqjvit4a",
        "link": "https://s.shopee.com.br/3B3tPpaSE7?utm_source=an_18318830863",
        "tags": [
            "#boutique"
        ],
        "reason": "Titanium Choice: Bem-Estar Íntimo",
        "added_date": "2026-04-30",
        "quality_score": 122.05070339926414
    },
    {
        "id": "sens_1777582908_740",
        "title": "Creme Hidratante Perfumado Sebo de Carneiro com Óleo de Argan 150g - Bio Instinto",
        "price": 15.99,
        "old_price": 21.59,
        "discount": 35,
        "store": "Shopee",
        "category": "Cosmética Sensorial",
        "image": "https://cf.shopee.com.br/file/br-11134207-7r98o-md0jfxkbsrup49",
        "link": "https://s.shopee.com.br/1qYVpO6Y0V?utm_source=an_18318830863",
        "tags": [
            "#elixir"
        ],
        "reason": "Titanium Choice: Bem-Estar Íntimo",
        "added_date": "2026-04-30",
        "quality_score": 76.24231401243101
    }
]