[
  {
    "data": "2026-02-12",
    "post_id": "17900102367380907",
    "imagem": "2026-02-12_mercadolivre_carnaval_de_ofertas.png",
    "loja": "mercadolivre",
    "categoria": "tecnologia",
    "tema": "Carnaval de Ofertas - Produtos com frete grátis e cashback no Mercado Livre",
    "timestamp": "2026-02-12T10:14:21.502992"
  },
  {
    "data": "2026-02-13",
    "post_id": "18043537715720514",
    "imagem": "2026-02-13_mercadolivre_decoracao.png",
    "loja": "mercadolivre",
    "categoria": "casa",
    "tema": "Decoração com preço especial - Renove sua casa com ofertas do Mercado Livre",
    "timestamp": "2026-02-13T11:08:08.557265"
  },
  {
    "data": "2026-02-20",
    "post_id": "17961594762018744",
    "imagem": "2026-02-20_amazon_ofertas_do_dia.jpeg",
    "loja": "amazon",
    "categoria": "tecnologia",
    "tema": "Ofertas do Dia Amazon - Os melhores preços e descontos para você economizar hoje",
    "timestamp": "2026-02-20T12:04:16.551488"
  },
  {
    "data": "2026-02-21",
    "post_id": "17924120328237815",
    "imagem": "2026-02-21_amazon_shopee_mercadolivre_dia_internacional_da_mulher.jpeg",
    "loja": "amazon",
    "categoria": "beleza",
    "tema": "Dia Internacional da Mulher - Celebre com ofertas exclusivas nas melhores lojas",
    "timestamp": "2026-02-21T11:01:51.220374"
  },
  {
    "data": "2026-02-22",
    "post_id": "17861315970536130",
    "imagem": "2026-02-22_amazon_shopee_mercadolivre_ofertas_do_dia.jpeg",
    "loja": "amazon",
    "categoria": "tecnologia",
    "tema": "Mega Ofertas do Dia - Amazon, Shopee e Mercado Livre com preços imbatíveis",
    "timestamp": "2026-02-22T15:16:26.317378"
  },
  {
    "data": "2026-02-23",
    "post_id": "17916231141127703",
    "imagem": "2026-02-23_mercadolivre_automotivo.png",
    "loja": "mercadolivre",
    "categoria": "automotivo",
    "tema": "Acessórios Automotivos - Ofertas especiais para o seu carro no Mercado Livre",
    "timestamp": "2026-02-23T11:31:58.492107"
  }
]